{"Metal": {"ariyalur": 100, "chengalpattu": 472, "chennai": 487, "coimbatore": 179, "cuddalore": 426, "dharmapuri": 307, "dindigul": 448, "erode": 308, "kallakurichi": 275, "kancheepuram": 439, "kanniyakumari": 382, "karur": 148, "krishnagiri": 351, "madurai": 309, "mayiladuthurai": 178, "nagapattinam": 181, "namakkal": 311, "perambalur": 358, "pudukkottai": 406, "ramanathapuram": 291, "ranipet": 334, "salem": 318, "sivagangai": 399, "tenkasi": 180, "thanjavur": 250, "theni": 257, "thoothukudi": 200, "tiruchirappalli": 282, "tirunelveli": 116, "tirupattur": 213, "tiruppur": 438, "tiruvallur": 203, "tiruvannamalai": 198, "tiruvarur": 153, "vellore": 251, "viluppuram": 168, "virudhunagar": 157}, "Fibre": {"ariyalur": 356, "chengalpattu": 159, "chennai": 385, "coimbatore": 119, "cuddalore": 147, "dharmapuri": 452, "dindigul": 275, "erode": 375, "kallakurichi": 376, "kancheepuram": 228, "kanniyakumari": 149, "karur": 380, "krishnagiri": 121, "madurai": 270, "mayiladuthurai": 481, "nagapattinam": 465, "namakkal": 259, "perambalur": 236, "pudukkottai": 162, "ramanathapuram": 442, "ranipet": 233, "salem": 237, "sivagangai": 426, "tenkasi": 132, "thanjavur": 481, "theni": 215, "thoothukudi": 397, "tiruchirappalli": 261, "tirunelveli": 423, "tirupattur": 245, "tiruppur": 284, "tiruvallur": 475, "tiruvannamalai": 380, "tiruvarur": 131, "vellore": 399, "viluppuram": 209, "virudhunagar": 348}, "Plastic": {"ariyalur": 245, "chengalpattu": 462, "chennai": 363, "coimbatore": 468, "cuddalore": 182, "dharmapuri": 310, "dindigul": 136, "erode": 232, "kallakurichi": 196, "kancheepuram": 344, "kanniyakumari": 477, "karur": 252, "krishnagiri": 472, "madurai": 297, "mayiladuthurai": 450, "nagapattinam": 103, "namakkal": 264, "perambalur": 364, "pudukkottai": 195, "ramanathapuram": 348, "ranipet": 322, "salem": 462, "sivagangai": 353, "tenkasi": 104, "thanjavur": 360, "theni": 446, "thoothukudi": 351, "tiruchirappalli": 220, "tirunelveli": 363, "tirupattur": 465, "tiruppur": 116, "tiruvallur": 188, "tiruvannamalai": 280, "tiruvarur": 352, "vellore": 208, "viluppuram": 494, "virudhunagar": 178}, "Rubber": {"ariyalur": 229, "chengalpattu": 167, "chennai": 217, "coimbatore": 267, "cuddalore": 416, "dharmapuri": 279, "dindigul": 391, "erode": 466, "kallakurichi": 146, "kancheepuram": 434, "kanniyakumari": 443, "karur": 232, "krishnagiri": 435, "madurai": 164, "mayiladuthurai": 194, "nagapattinam": 146, "namakkal": 474, "perambalur": 143, "pudukkottai": 469, "ramanathapuram": 138, "ranipet": 273, "salem": 103, "sivagangai": 264, "tenkasi": 336, "thanjavur": 373, "theni": 255, "thoothukudi": 357, "tiruchirappalli": 324, "tirunelveli": 227, "tirupattur": 175, "tiruppur": 448, "tiruvallur": 304, "tiruvannamalai": 151, "tiruvarur": 341, "vellore": 201, "viluppuram": 496, "virudhunagar": 286}}